easy_color_yy/__init__.py
easy_color_yy/color.py
easy_color_yy-0.1.0.dist-info/METADATA
easy_color_yy-0.1.0.dist-info/WHEEL
easy_color_yy-0.1.0.dist-info/top_level.txt
easy_color_yy-0.1.0.dist-info/RECORD
